flippyr.py
flippyr-0.6.1.dist-info/LICENSE
flippyr-0.6.1.dist-info/METADATA
flippyr-0.6.1.dist-info/WHEEL
flippyr-0.6.1.dist-info/entry_points.txt
flippyr-0.6.1.dist-info/top_level.txt
flippyr-0.6.1.dist-info/RECORD
