Metadata-Version: 2.1
Name: flippyr
Version: 0.6.1
Summary: Find reference mismatches in PLINK filesets and fix them.
Home-page: https://github.com/BEFH/flippyr
Author: Brian Fulton-Howard
Author-email: brian.fulton-howard@mssm.edu
License: MIT
Keywords: bim PLINK FASTA genomics qc
Classifier: Development Status :: 3 - Alpha
Classifier: Intended Audience :: Science/Research
Classifier: Topic :: Scientific/Engineering
Classifier: License :: OSI Approved :: MIT License
Classifier: Programming Language :: Python :: 3
Classifier: Programming Language :: Python :: 3.9
Classifier: Programming Language :: Python :: 3.10
Classifier: Programming Language :: Python :: 3.11
Classifier: Programming Language :: Python :: 3.12
Classifier: Operating System :: POSIX :: Linux
Classifier: Operating System :: MacOS :: MacOS X
Classifier: Operating System :: Microsoft
License-File: LICENSE
Requires-Dist: pyfaidx
Requires-Dist: pandas
